setup.py
Calculadora.egg-info/PKG-INFO
Calculadora.egg-info/SOURCES.txt
Calculadora.egg-info/dependency_links.txt
Calculadora.egg-info/top_level.txt
calculadora/__init__.py
calculadora/calculadora.py