Metadata-Version: 1.0
Name: Calculadora
Version: 0.1
Summary: Calculadora básica
Home-page: http://devcode.la
Author: Devcode.la
Author-email: hola@devcode.la
License: UNKNOWN
Platform: UNKNOWN
